techdevutil
