Metadata-Version: 1.1
Name: techdevutil
Version: 0.0.2
Summary: A util library
Home-page: UNKNOWN
Author: techpluscraft
Author-email: techpluscraft@gmail.com
License: MIT
Keywords: util
Platform: UNKNOWN
Classifier: Development Status :: 5 - Production/Stable
Classifier: Intended Audience :: Education
Classifier: Operating System :: Microsoft :: Windows :: Windows 10
Classifier: License :: OSI Approved :: MIT License
Classifier: Programming Language :: Python :: 3
